MANIFEST.in
README.rst
pog.py
setup.py
pog.egg-info/PKG-INFO
pog.egg-info/SOURCES.txt
pog.egg-info/dependency_links.txt
pog.egg-info/top_level.txt