Metadata-Version: 1.1
Name: pog
Version: 0.0.1
Summary: Azkaban CLI
Home-page: http://github.com/mtth/pog/
Author: Matthieu Monsch
Author-email: monsch@alum.mit.edu
License: MIT
Platform: UNKNOWN
Classifier: Development Status :: 2 - Pre-Alpha
Classifier: Intended Audience :: Developers
Classifier: License :: OSI Approved :: MIT License
Classifier: Programming Language :: Python
